quizml/__init__.py
quizml/__main__.py
quizml/cache.py
quizml/docx_renderer.py
quizml/exceptions.py
quizml/loader.py
quizml/renderer.py
quizml/utils.py
quizml/cli/__init__.py
quizml/cli/cleanup.py
quizml/cli/cli.py
quizml/cli/compile.py
quizml/cli/config.py
quizml/cli/diff.py
quizml/cli/errorhandler.py
quizml/cli/filelocator.py
quizml/cli/init.py
quizml/cli/livereload.py
quizml/cli/shellcompletion.py
quizml/cli/ui.py
quizml/markdown/__init__.py
quizml/markdown/extensions.py
quizml/markdown/html_renderer.py
quizml/markdown/image_embedding.py
quizml/markdown/latex_renderer.py
quizml/markdown/latextools.py
quizml/markdown/markdown.py
quizml/markdown/utils.py
quizml/templates/blackboard.txt.j2
quizml/templates/create_docx_template.py
quizml/templates/markdown-html.css
quizml/templates/math-preamble.tex
quizml/templates/omrglyphs.sty
quizml/templates/preview.html.j2
quizml/templates/prototype.docx
quizml/templates/quizml.cfg
quizml/templates/schema.json
quizml/templates/stats.txt.j2
quizml/templates/tcd-exam-solutions.tex.j2
quizml/templates/tcd-exam.tex.j2
quizml-0.10.0.dist-info/licenses/LICENSE
quizml-0.10.0.dist-info/METADATA
quizml-0.10.0.dist-info/WHEEL
quizml-0.10.0.dist-info/entry_points.txt
quizml-0.10.0.dist-info/top_level.txt
quizml-0.10.0.dist-info/RECORD
