Metadata-Version: 2.4
Name: quizml
Version: 0.10.0
Summary:   Tool for converting a list of questions in yaml/markdown to aBlackBoard test or to a Latex exam source file
Author-email: Francois Pitie <francois.pitie@gmail.com>
License: GPLv3
Project-URL: Repository, https://github.com/frcs/quizml.git
Project-URL: Homepage, https://frcs.github.io/quizml
Keywords: BlackBoard,exam,test,quiz,MCQ,YAML,Markdown,Latex
Requires-Python: >=3.8
License-File: LICENSE
Requires-Dist: pillow
Requires-Dist: ruamel.yaml>=0.17
Requires-Dist: jsonschema>=4.0
Requires-Dist: bs4
Requires-Dist: rich>=14.0.0
Requires-Dist: rich-argparse
Requires-Dist: jinja2
Requires-Dist: colorama
Requires-Dist: watchdog
Requires-Dist: mistletoe==1.3.0
Requires-Dist: css_inline
Requires-Dist: latex2mathml
Requires-Dist: appdirs
Requires-Dist: docxtpl
Dynamic: license-file
